beam_sink/__init__.py
beam_sink/sinks/__init__.py
beam_sink/sinks/mysql.py
beam_sink/sinks/postgres.py
tests/__init__.py
tests/test_mysql.py
tests/test_postgres.py
beam_sink-1.0.1.dist-info/LICENSE
beam_sink-1.0.1.dist-info/METADATA
beam_sink-1.0.1.dist-info/WHEEL
beam_sink-1.0.1.dist-info/top_level.txt
beam_sink-1.0.1.dist-info/RECORD
